README.md
setup.py
scripts/concat-parquet
scripts/dump-parquet
scripts/ge-dump-parquet
scripts/load-graph-embeddings
scripts/load-triples
scripts/triples-dump-parquet
trustgraph/parquet_version.py
trustgraph/dump/__init__.py
trustgraph/dump/graph_embeddings/__init__.py
trustgraph/dump/graph_embeddings/parquet/__init__.py
trustgraph/dump/graph_embeddings/parquet/__main__.py
trustgraph/dump/graph_embeddings/parquet/processor.py
trustgraph/dump/graph_embeddings/parquet/writer.py
trustgraph/dump/triples/__init__.py
trustgraph/dump/triples/parquet/__init__.py
trustgraph/dump/triples/parquet/__main__.py
trustgraph/dump/triples/parquet/processor.py
trustgraph/dump/triples/parquet/writer.py
trustgraph_parquet.egg-info/PKG-INFO
trustgraph_parquet.egg-info/SOURCES.txt
trustgraph_parquet.egg-info/dependency_links.txt
trustgraph_parquet.egg-info/requires.txt
trustgraph_parquet.egg-info/top_level.txt