Metadata-Version: 2.1
Name: trustgraph-parquet
Version: 0.17.1
Summary: TrustGraph provides a means to run a pipeline of flexible AI processing components in a flexible means to achieve a processing pipeline.
Home-page: https://github.com/trustgraph-ai/trustgraph
Author: trustgraph.ai
Author-email: security@trustgraph.ai
License: UNKNOWN
Download-URL: https://github.com/trustgraph-ai/trustgraph/archive/refs/tags/v0.17.1.tar.gz
Platform: UNKNOWN
Classifier: Programming Language :: Python :: 3
Classifier: License :: OSI Approved :: GNU General Public License v3 or later (GPLv3+)
Classifier: Operating System :: OS Independent
Requires-Python: >=3.8
